tfmcutil/__init__.py
tfmcutil/tfmcutil.py
tfmcutil-0.0.2.dist-info/LICENSE
tfmcutil-0.0.2.dist-info/METADATA
tfmcutil-0.0.2.dist-info/WHEEL
tfmcutil-0.0.2.dist-info/top_level.txt
tfmcutil-0.0.2.dist-info/RECORD
