Metadata-Version: 2.1
Name: tfmcutil
Version: 0.0.2
Summary: 文本文件合并、分割小模块：练习用。
Home-page: https://gitee.com/hrpzcf/tfmcutil
Author: hrpzcf
Author-email: hrpzcf@foxmail.com
Maintainer: hrpzcf
Maintainer-email: hrpzcf@foxmail.com
License: MIT License
Keywords: text file,merge,cut up
Platform: UNKNOWN
Classifier: Intended Audience :: Developers
Classifier: Development Status :: 4 - Beta
Classifier: License :: OSI Approved :: MIT License
Classifier: Programming Language :: Python :: 3.7
Classifier: Programming Language :: Python :: 3.8
Classifier: Programming Language :: Python :: 3.9
Requires-Python: >=3.7
Requires-Dist: chardet (>=4.0)
